truxautomation/__init__.py
truxautomation/print.py
truxautomation/imgs/__init__.py
truxautomation-0.0.5.dist-info/METADATA
truxautomation-0.0.5.dist-info/WHEEL
truxautomation-0.0.5.dist-info/top_level.txt
truxautomation-0.0.5.dist-info/RECORD
