Metadata-Version: 2.1
Name: truxautomation
Version: 0.0.5
Summary: A small python package for automating tasks within Trux.
Author: Nevil Mills
Author-email: <youremail@email.com>
Keywords: python,first package
Classifier: Development Status :: 3 - Alpha
Classifier: Intended Audience :: Education
Classifier: Programming Language :: Python :: 2
Classifier: Programming Language :: Python :: 3
Classifier: Operating System :: MacOS :: MacOS X
Classifier: Operating System :: Microsoft :: Windows
Requires-Dist: pyautogui
Requires-Dist: Pillow
